{
  "file_path": "c:\\Users\\sgbil\\OneDrive\\Desktop\\Negative_Space_Imaging_Project\\.venv\\Lib\\site-packages\\fontTools\\varLib\\interpolatable.py",
  "classes": [
    {
      "name": "Glyph",
      "docstring": null,
      "methods": [
        {
          "name": "__init__",
          "docstring": null
        },
        {
          "name": "draw",
          "docstring": null
        }
      ]
    }
  ],
  "functions": [
    {
      "name": "test_gen",
      "docstring": null
    },
    {
      "name": "test",
      "docstring": null
    },
    {
      "name": "recursivelyAddGlyph",
      "docstring": null
    },
    {
      "name": "ensure_parent_dir",
      "docstring": null
    },
    {
      "name": "main",
      "docstring": "Test for interpolatability issues between fonts"
    },
    {
      "name": "draw",
      "docstring": null
    },
    {
      "name": "grand_parent",
      "docstring": null
    }
  ],
  "innovations": []
}