{
  "file_path": "c:\\Users\\sgbil\\OneDrive\\Desktop\\Negative_Space_Imaging_Project\\.venv\\Lib\\site-packages\\PIL\\MpegImagePlugin.py",
  "classes": [
    {
      "name": "BitStream",
      "docstring": null,
      "methods": [
        {
          "name": "__init__",
          "docstring": null
        },
        {
          "name": "next",
          "docstring": null
        },
        {
          "name": "peek",
          "docstring": null
        },
        {
          "name": "skip",
          "docstring": null
        },
        {
          "name": "read",
          "docstring": null
        }
      ]
    },
    {
      "name": "MpegImageFile",
      "docstring": null,
      "methods": []
    }
  ],
  "functions": [
    {
      "name": "next",
      "docstring": null
    },
    {
      "name": "peek",
      "docstring": null
    },
    {
      "name": "skip",
      "docstring": null
    },
    {
      "name": "read",
      "docstring": null
    }
  ],
  "innovations": []
}