{
  "file_path": "c:\\Users\\sgbil\\OneDrive\\Desktop\\Negative_Space_Imaging_Project\\.venv\\Lib\\site-packages\\fontTools\\misc\\py23.py",
  "classes": [
    {
      "name": "Py23Error",
      "docstring": null,
      "methods": []
    }
  ],
  "functions": [
    {
      "name": "xrange",
      "docstring": null
    },
    {
      "name": "round2",
      "docstring": "Implementation of Python 2 built-in round() function.\nRounds a number to a given precision in decimal digits (default\n0 digits). The result is a floating point number. Values are rounded\nto the closest multiple of 10 to the power minus ndigits; if two\nmultiples are equally close, rounding is done away from 0.\nndigits may be negative.\nSee Python 2 documentation:\nhttps://docs.python.org/2/library/functions.html?highlight=round#round"
    }
  ],
  "innovations": []
}