{
  "file_path": "c:\\Users\\sgbil\\OneDrive\\Desktop\\Negative_Space_Imaging_Project\\.venv\\Lib\\site-packages\\PIL\\TarIO.py",
  "classes": [
    {
      "name": "TarIO",
      "docstring": "A file object that provides read access to a given member of a TAR file.",
      "methods": [
        {
          "name": "__init__",
          "docstring": "Create file object.\n\n:param tarfile: Name of TAR file.\n:param file: Name of member file."
        }
      ]
    }
  ],
  "functions": [],
  "innovations": []
}