{
  "file_path": "c:\\Users\\sgbil\\OneDrive\\Desktop\\Negative_Space_Imaging_Project\\.venv\\Lib\\site-packages\\fontTools\\ttLib\\tables\\ttProgram.py",
  "classes": [
    {
      "name": "tt_instructions_error",
      "docstring": null,
      "methods": [
        {
          "name": "__init__",
          "docstring": null
        }
      ]
    },
    {
      "name": "Program",
      "docstring": null,
      "methods": [
        {
          "name": "__init__",
          "docstring": null
        },
        {
          "name": "fromBytecode",
          "docstring": null
        },
        {
          "name": "fromAssembly",
          "docstring": null
        },
        {
          "name": "getBytecode",
          "docstring": null
        },
        {
          "name": "getAssembly",
          "docstring": null
        },
        {
          "name": "toXML",
          "docstring": null
        },
        {
          "name": "fromXML",
          "docstring": null
        }
      ]
    }
  ],
  "functions": [
    {
      "name": "bitRepr",
      "docstring": null
    },
    {
      "name": "fromBytecode",
      "docstring": null
    },
    {
      "name": "fromAssembly",
      "docstring": null
    },
    {
      "name": "getBytecode",
      "docstring": null
    },
    {
      "name": "getAssembly",
      "docstring": null
    },
    {
      "name": "toXML",
      "docstring": null
    },
    {
      "name": "fromXML",
      "docstring": null
    }
  ],
  "innovations": []
}